CHANGELOG.md
activeconfigprogramoptions/ActiveConfigProgramOptions.py
activeconfigprogramoptions/ActiveConfigProgramOptionsCMake.py
activeconfigprogramoptions/__init__.py
activeconfigprogramoptions/common.py
activeconfigprogramoptions/unittests/__init__.py
activeconfigprogramoptions/unittests/common.py
activeconfigprogramoptions/unittests/files_ini/config_test_activeconfigprogramoptions.ini
activeconfigprogramoptions/unittests/test_ActiveConfigProgramOptions.py
activeconfigprogramoptions/unittests/test_ActiveConfigProgramOptionsCMake.py
activeconfigprogramoptions/version.py
activeconfigprogramoptions-0.6.0.1.dist-info/LICENSE
activeconfigprogramoptions-0.6.0.1.dist-info/METADATA
activeconfigprogramoptions-0.6.0.1.dist-info/WHEEL
activeconfigprogramoptions-0.6.0.1.dist-info/RECORD
