Metadata-Version: 2.1
Name: activeconfigprogramoptions
Version: 0.6.0.1
Summary: Program options configuration file reader using ActiveConfigParser.
Home-page: https://gitlab.com/semantik-software/code/python/ActiveConfigProgramOptions
License: LICENSE
Keywords: Utility,Bash,Configuration,ActiveConfigParser,ConfigParser
Author: William
Author-email: Semantik-Codeworks@outlook.com
Maintainer: William
Maintainer-email: Semantik-Codeworks@outlook.com
Requires-Python: >=3.6
Classifier: Development Status :: 5 - Production/Stable
Classifier: Intended Audience :: Developers
Classifier: Intended Audience :: Other Audience
Classifier: Intended Audience :: System Administrators
Classifier: License :: OSI Approved :: BSD License
Classifier: License :: Other/Proprietary License
Classifier: Programming Language :: Python :: 3
Classifier: Programming Language :: Python :: 3.6
Classifier: Programming Language :: Python :: 3.7
Classifier: Programming Language :: Python :: 3.8
Classifier: Programming Language :: Python :: 3.9
Classifier: Programming Language :: Python :: 3.10
Classifier: Programming Language :: Python :: 3.11
Classifier: Programming Language :: Python :: 3 :: Only
Requires-Dist: activeconfigparser (>=0.9)
Requires-Dist: configparser (>=5.0)
Requires-Dist: exceptioncontrol (>=0.1)
Requires-Dist: stronglytypedproperty (>=0.1)
Project-URL: Documentation, https://semantik-software.gitlab.io/code/python/ActiveConfigProgramOptions
Project-URL: Repository, https://gitlab.com/semantik-software/code/python/ActiveConfigProgramOptions
